MANIFEST.in
README.rst
VERSION
setup.py
MangoEngine.egg-info/PKG-INFO
MangoEngine.egg-info/SOURCES.txt
MangoEngine.egg-info/dependency_links.txt
MangoEngine.egg-info/top_level.txt
mangoengine/__init__.py
mangoengine/errors.py
mangoengine/fields.py
mangoengine/models.py
mangoengine/tests/__init__.py
mangoengine/tests/test_fields.py
mangoengine/tests/test_models.py