Metadata-Version: 1.1
Name: MangoEngine
Version: v1.0.0-rc.1
Summary: MangoEngine is a lightweight library for creating generic data models in Python.
Home-page: https://www.github.com/brownhead/mangoengine
Author: John Sullivan
Author-email: john@galahgroup.com
License: Unlicense
Keywords: json python models
Platform: UNKNOWN
Classifier: License :: Public Domain
